ip_query/GeoLite2-ASN.py
ip_query/GeoLite2-Country.py
ip_query/__init__.py
ip_query/ip_query.py
ip_query-4.3.1.dist-info/LICENSE
ip_query-4.3.1.dist-info/METADATA
ip_query-4.3.1.dist-info/WHEEL
ip_query-4.3.1.dist-info/top_level.txt
ip_query-4.3.1.dist-info/RECORD
