Metadata-Version: 2.1
Name: ip-query
Version: 4.3.1
Summary: Python IP Query.
Home-page: https://github.com/voken100g/python-ip-query
Author: Vision Network
Author-email: michael@vision.network
License: UNKNOWN
Keywords: IP,IP address,IP GEO
Platform: UNKNOWN
Classifier: Programming Language :: Python :: 3
Classifier: License :: OSI Approved :: MIT License
Classifier: Operating System :: OS Independent
Requires-Dist: requests[socks]
Requires-Dist: geoip2
Requires-Dist: cli-print
